sunset/__init__.py
sunset/autoloader.py
sunset/autosaver.py
sunset/bunch.py
sunset/enum_serializer.py
sunset/exporter.py
sunset/key.py
sunset/list.py
sunset/lock.py
sunset/notifier.py
sunset/protocols.py
sunset/py.typed
sunset/serializers.py
sunset/sets.py
sunset/settings.py
sunset/stringutils.py
sunset/timer.py
sunsetsettings-0.7.0.dist-info/METADATA
sunsetsettings-0.7.0.dist-info/WHEEL
sunsetsettings-0.7.0.dist-info/licenses/LICENSE
sunsetsettings-0.7.0.dist-info/RECORD
