Metadata-Version: 2.4
Name: SunsetSettings
Version: 0.7.0
Summary: A type-safe, extensible INI-style settings library.
Project-URL: Home, https://github.com/pvaret/SunsetSettings
Project-URL: Documentation, https://sunsetsettings.readthedocs.io/
Author-email: "P. Varet" <p.varet@gmail.com>
License:                     GNU GENERAL PUBLIC LICENSE
License-File: LICENSE
Classifier: Development Status :: 5 - Production/Stable
Classifier: Intended Audience :: Developers
Classifier: License :: OSI Approved :: GNU General Public License v3 or later (GPLv3+)
Classifier: Operating System :: OS Independent
Classifier: Programming Language :: Python
Classifier: Programming Language :: Python :: 3 :: Only
Classifier: Programming Language :: Python :: 3.10
Classifier: Programming Language :: Python :: 3.11
Classifier: Programming Language :: Python :: 3.12
Classifier: Programming Language :: Python :: 3.13
Classifier: Topic :: Software Development :: Libraries :: Python Modules
Classifier: Typing :: Typed
Requires-Python: >=3.10
Requires-Dist: typing-extensions; python_version == '3.10'
Provides-Extra: docs
Requires-Dist: sphinx; extra == 'docs'
Requires-Dist: sphinx-rtd-theme; extra == 'docs'
Provides-Extra: tests
Requires-Dist: coverage[toml]; extra == 'tests'
Requires-Dist: pytest; extra == 'tests'
Requires-Dist: pytest-cov; extra == 'tests'
Requires-Dist: pytest-mock; extra == 'tests'
Requires-Dist: pytest-skip-slow; extra == 'tests'
